toolcache/__init__.py
toolcache/cache_decorator.py
toolcache/hash_utils.py
toolcache/py.typed
toolcache/spec.py
toolcache/cachetypes/__init__.py
toolcache/cachetypes/cachetype_utils.py
toolcache/cachetypes/disk_cache.py
toolcache/cachetypes/memory_cache.py
toolcache/cachetypes/null_cache.py
toolcache/cachetypes/base_cache/__init__.py
toolcache/cachetypes/base_cache/base_cache.py
toolcache/cachetypes/base_cache/base_cache_child_methods.py
toolcache/cachetypes/base_cache/base_cache_crud.py
toolcache/cachetypes/base_cache/base_cache_eviction.py
toolcache/cachetypes/base_cache/base_cache_hash.py
toolcache/cachetypes/base_cache/base_cache_stats.py
toolcache-0.5.0.dist-info/LICENSE
toolcache-0.5.0.dist-info/WHEEL
toolcache-0.5.0.dist-info/METADATA
toolcache-0.5.0.dist-info/RECORD
