Metadata-Version: 2.1
Name: toolcache
Version: 0.5.0
Summary: toolcache makes it easy to create and configure caches in memory or on disk
Requires-Python: >=3.7
Requires-Dist: tooltime
Requires-Dist: typing_extensions
